LayerObjects.cpython-37m-darwin.so
ReanalysisMatch.cpython-37m-darwin.so
cloud_type_identification/__init__.py
cloud_type_identification/cloudTypeExe.py
cloud_type_identification/cloud_types.py
cloudsat_object_manipulation/__init__.py
cloudsat_object_manipulation/cldObj_creation.py
cloudsat_object_manipulation/cloud_stats.py
cloudsat_object_manipulation/objCreate.py
land_sea_mask/__init__.py
land_sea_mask/createLSM.py
land_sea_mask/landSeaMaskCreate.py
precipitation_manipulation/__init__.py
precipitation_manipulation/precipAnalysis.py
precipitation_manipulation/precipitationMatch.py
rh_match/__init__.py
rh_match/__main__.py
rh_match/rhMatch.py
tcwv_match/__init__.py
tcwv_match/__main__.py
tcwv_match/tcwvID.py
tests/__init__.py
tests/test_cloudsat_object_manipulation.py
cloudsat_object_manipulation-0.1.11.dist-info/LICENSE
cloudsat_object_manipulation-0.1.11.dist-info/METADATA
cloudsat_object_manipulation-0.1.11.dist-info/WHEEL
cloudsat_object_manipulation-0.1.11.dist-info/entry_points.txt
cloudsat_object_manipulation-0.1.11.dist-info/top_level.txt
cloudsat_object_manipulation-0.1.11.dist-info/RECORD
