Metadata-Version: 2.1
Name: cloudsat-object-manipulation
Version: 0.1.11
Summary: This package contains a set of packages and command line plugins that can identify indidual cloud objects along CloudSat's orbit and their associated properties (i.e. cloud type, size, precipitating)
Home-page: https://github.com/kms22134/cloudsat_manipulation
Author: Kevin Smalley
Author-email: ksmalley@tamu.edu
License: MIT license
Keywords: cloudsat_object_manipulation
Platform: UNKNOWN
Classifier: Development Status :: 2 - Pre-Alpha
Classifier: Intended Audience :: Developers
Classifier: License :: OSI Approved :: MIT License
Classifier: Natural Language :: English
Classifier: Environment :: Console
Classifier: Intended Audience :: Science/Research
Classifier: Topic :: Scientific/Engineering :: Atmospheric Science
Classifier: Operating System :: MacOS
Classifier: Operating System :: POSIX :: Linux
Classifier: Programming Language :: C
Classifier: Programming Language :: C++
Classifier: Programming Language :: Cython
Classifier: Programming Language :: Python :: 2
Classifier: Programming Language :: Python :: 2.7
Classifier: Programming Language :: Python :: 3
Classifier: Programming Language :: Python :: 3.4
Classifier: Programming Language :: Python :: 3.5
Classifier: Programming Language :: Python :: 3.6
Classifier: Programming Language :: Python :: 3.7
Requires-Dist: h5py
Requires-Dist: pandas
Requires-Dist: numpy
Requires-Dist: scipy
Requires-Dist: xarray
Requires-Dist: netcdf4
